synapse_protobuf/__init__.py
synapse_protobuf/actuators_pb2.py
synapse_protobuf/altimeter_pb2.py
synapse_protobuf/battery_state_pb2.py
synapse_protobuf/bezier_curve_pb2.py
synapse_protobuf/bezier_trajectory_pb2.py
synapse_protobuf/bit32_flag_pb2.py
synapse_protobuf/can_pb2.py
synapse_protobuf/frame_pb2.py
synapse_protobuf/header_pb2.py
synapse_protobuf/imu_pb2.py
synapse_protobuf/input_pb2.py
synapse_protobuf/led_array_pb2.py
synapse_protobuf/led_pb2.py
synapse_protobuf/magnetic_field_pb2.py
synapse_protobuf/nav_sat_fix_pb2.py
synapse_protobuf/nav_sat_status_pb2.py
synapse_protobuf/odometry_pb2.py
synapse_protobuf/point_pb2.py
synapse_protobuf/pose_pb2.py
synapse_protobuf/pose_with_covariance_pb2.py
synapse_protobuf/pwm_pb2.py
synapse_protobuf/quaternion_pb2.py
synapse_protobuf/safety_pb2.py
synapse_protobuf/sim_clock_pb2.py
synapse_protobuf/snap_setpoint_pb2.py
synapse_protobuf/status_pb2.py
synapse_protobuf/time_pb2.py
synapse_protobuf/twist_pb2.py
synapse_protobuf/twist_with_covariance_pb2.py
synapse_protobuf/vector3_pb2.py
synapse_protobuf/wheel_odometry_pb2.py
synapse_protobuf-0.1.4.dist-info/METADATA
synapse_protobuf-0.1.4.dist-info/WHEEL
synapse_protobuf-0.1.4.dist-info/RECORD
