Metadata-Version: 2.1
Name: synapse-protobuf
Version: 0.1.4
Summary: 
License: Apache 2.0
Author: James Goppert
Author-email: james.goppert@gmail.com
Requires-Python: >=3.10,<4.0
Classifier: License :: Other/Proprietary License
Classifier: Programming Language :: Python :: 3
Classifier: Programming Language :: Python :: 3.10
Classifier: Programming Language :: Python :: 3.11
Classifier: Programming Language :: Python :: 3.12
Requires-Dist: protobuf (>=3.20.0,<4.0.0)
